{
  "tasks": [
    [{ "image": "klimov", "name": "Ухаживать за животными" }, { "image": "", "name": "Обслуживать машины, приборы (следить, регулировать)" }],
    [{ "image": "", "name": "Помогать больным" }, { "image": "", "name": "Составлять таблицы, схемы, программы для вычислительных машин"}],
    [{ "image": "", "name": "Следить за качеством книжных иллюстраций, плакатов, художественных открыток, грампластинок" }, { "image": "", "name": "Следить за состоянием, развитием растений" }],
    [{ "image": "", "name": " Обрабатывать материалы (дерево, ткань, металл, пластмассу и т.п.)" }, { "image": "", "name": "Доводить Товары до потребителя, рекламировать, продавать" }],
    [{ "image": "", "name": "Обсуждать научно-популярные книги, статьи" }, { "image": "", "name": "Обсуждать художественные книги (или пьесы, концерты)" }],
    [{ "image": "", "name": "Выращивать молодняк (животных какой-либо породы)" }, { "image": "", "name": " Тренировать товарищей (или младших) в выполнении каких-либо действий (трудовых, учебных, спортивных)" }],
    [{ "image": "", "name": "Копировать рисунки, изображения (или настраивать музыкальные инструменты)" }, { "image": "", "name": "Управлять каким-либо грузовым (подъемным или транспортным) средством – подъемным краном, трактором, тепловозом и др." }],
    [{ "image": "", "name": "Сообщать, разъяснять людям нужные им сведения (в справочном бюро, на экскурсии и т.д.)" }, { "image": "", "name": "Оформлять выставки, витрины (или участвовать в подготовке пьес, концертов)" }],
    [{ "image": "", "name": "Ремонтировать вещи, изделия (одежду, технику), жилище" }, { "image": "", "name": "Искать и исправлять ошибки в текстах, таблицах, рисунках" }],
    [{ "image": "", "name": "Лечить животных" }, { "image": "", "name": "Выполнять вычисления, расчеты" }],
    [{ "image": "", "name": "Выводить новые сорта растений" }, { "image": "", "name": "Конструировать, проектировать новые виды промышленных изделий (машины, одежду, дома, продукты питания и т.п.)" }],
    [{ "image": "", "name": "Разбирать споры, ссоры между людьми, убеждать, разъяснять, наказывать, поощрять" }, { "image": "", "name": "Разбираться в чертежах, схемах, таблицах (проверять, уточнять, приводить в порядок)" }],
    [{ "image": "", "name": "Наблюдать, изучать работу кружков художественной самодеятельности" }, { "image": "", "name": "Наблюдать, изучать жизнь микробов" }],
    [{ "image": "", "name": "Обслуживать, налаживать медицинские приборы, аппараты" }, { "image": "", "name": "Оказывать людям медицинскую помощь при ранениях, ушибах, ожогах и т.п." }],
    [{ "image": "", "name": "Художественно описывать, изображать события (наблюдаемые и представляемые)" }, { "image": "", "name": "Составлять точные описания-отчеты о наблюдаемых явлениях, событиях, измеряемых объектах и др." }],
    [{ "image": "", "name": "Делать лабораторные анализы в больнице" }, { "image": "", "name": "Принимать, осматривать больных, беседовать с ними, назначать лечение" }],
    [{ "image": "", "name": "Красить или расписывать стены помещений, поверхность изделий" }, { "image": "", "name": "Осуществлять монтаж или сборку машин, приборов" }],
    [{ "image": "", "name": "Организовать культпоходы сверстников или младших в театры, музеи, экскурсии, туристические походы и т.п." }, { "image": "", "name": "Играть на сцене, принимать участие в концертах" }],
    [{ "image": "", "name": "Изготовлять по чертежам детали, изделия (машины, одежду), строить здания" }, { "image": "", "name": "Заниматься черчением, копировать чертежи, карты" }],
    [{ "image": "", "name": "Вести борьбу с болезнями растений, с вредителями леса, сада" }, { "image": "", "name": "Работать на клавишных машинах (пишущей машинке, телетайпе, наборной машине и др.)" }]
  ],
  "answers": {
    "nature": [
      { "num": 1, "answer": false },
      { "num": 3, "answer": true },
      { "num": 6, "answer": false },
      { "num": 10, "answer": false },
      { "num": 11, "answer": false },
      { "num": 13, "answer": true },
      { "num": 16, "answer": false },
      { "num": 20, "answer": false }
    ],
    "technics": [
      { "num": 1, "answer": true },
      { "num": 4, "answer": false },
      { "num": 7, "answer": true },
      { "num": 9, "answer": false },
      { "num": 11, "answer": true },
      { "num": 14, "answer": false },
      { "num": 17, "answer": true },
      { "num": 19, "answer": false }
    ],
    "human": [
      { "num": 2, "answer": false },
      { "num": 4, "answer": true },
      { "num": 6, "answer": true },
      { "num": 8, "answer": false },
      { "num": 12, "answer": false },
      { "num": 14, "answer": true },
      { "num": 16, "answer": true },
      { "num": 18, "answer": false }
    ],
    "signSystem": [
      { "num": 2, "answer": true },
      { "num": 5, "answer": false },
      { "num": 9, "answer": true },
      { "num": 10, "answer": true },
      { "num": 12, "answer": true },
      { "num": 15, "answer": false },
      { "num": 19, "answer": true },
      { "num": 20, "answer": true }
    ],
    "artisticImage": [
      { "num": 3, "answer": false },
      { "num": 5, "answer": true },
      { "num": 7, "answer": false },
      { "num": 8, "answer": true },
      { "num": 13, "answer": false },
      { "num": 15, "answer": true },
      { "num": 17, "answer": false },
      { "num": 18, "answer": true }
    ]
  }
}